dglib3/__init__.py
dglib3/cache_util.py
dglib3/codecs.py
dglib3/db_util.py
dglib3/dumper.py
dglib3/logutil.py
dglib3/tracer.py
dglib3/utils.py
dglib3/win_util.py
dglib3/basis/__init__.py
dglib3/basis/ordered_dict.py
dglib3/basis/pydicti.py
dglib3/basis/singleton.py
dglib3/config/__init__.py
dglib3/config/inifiles.py
dglib3-1.6.2.dist-info/LICENSE
dglib3-1.6.2.dist-info/METADATA
dglib3-1.6.2.dist-info/WHEEL
dglib3-1.6.2.dist-info/top_level.txt
dglib3-1.6.2.dist-info/RECORD
