Metadata-Version: 2.1
Name: dglib3
Version: 1.6.2
Summary: Daemon glance lib (for py3)
Home-page: https://github.com/ddcatgg/dglib3
Download-URL: 
Author: DDGG
Author-email: 990080@qq.com
Keywords: util,tool,ddgg
Classifier: Programming Language :: Python
Classifier: Programming Language :: Python :: 3.5
Classifier: Programming Language :: Python :: 3.6
Classifier: Programming Language :: Python :: 3.7
Classifier: Development Status :: 4 - Beta
Classifier: Environment :: Other Environment
Classifier: Intended Audience :: Developers
Classifier: License :: OSI Approved :: MIT License
Classifier: Operating System :: Microsoft :: Windows
Classifier: Topic :: Software Development :: Libraries :: Python Modules
Classifier: Topic :: Utilities
License-File: LICENSE
